{"type":"FeatureCollection","name":"点","features":[{"type":"Feature","properties":{"NAME":"昆明市","QUHUADAIMA":"530100","Location":2,"Alignment":2},"geometry":{"type":"Point","coordinates":[102.95349325958757,25.019648927422036]}},{"type":"Feature","properties":{"NAME":"临沧市","QUHUADAIMA":"530900","Location":4,"Alignment":3},"geometry":{"type":"Point","coordinates":[100.21931004486032,24.010704587312215]}},{"type":"Feature","properties":{"NAME":"玉溪市","QUHUADAIMA":"530400","Location":4,"Alignment":3},"geometry":{"type":"Point","coordinates":[102.66849031350874,24.481323793535022]}},{"type":"Feature","properties":{"NAME":"保山市","QUHUADAIMA":"530500","Location":4,"Alignment":3},"geometry":{"type":"Point","coordinates":[99.287396271167438,25.245425274664061]}},{"type":"Feature","properties":{"NAME":"曲靖市","QUHUADAIMA":"530300","Location":2,"Alignment":2},"geometry":{"type":"Point","coordinates":[103.92110350813445,25.618642961266872]}},{"type":"Feature","properties":{"NAME":"昭通市","QUHUADAIMA":"530600","Location":4,"Alignment":3},"geometry":{"type":"Point","coordinates":[103.84409948748036,27.472836309089]}},{"type":"Feature","properties":{"NAME":"普洱市","QUHUADAIMA":"530800","Location":4,"Alignment":3},"geometry":{"type":"Point","coordinates":[101.09807691995617,22.913233350642198]}},{"type":"Feature","properties":{"NAME":"丽江市","QUHUADAIMA":"530700","Location":3,"Alignment":1},"geometry":{"type":"Point","coordinates":[100.36172984649079,27.002530469048146]}}]}